README.md
setup.py
galileo/__init__.py
galileo/util.py
galileo/apps/__init__.py
galileo/apps/app.py
galileo/apps/loader.py
galileo/apps/repository.py
galileo/cli/__init__.py
galileo/cli/experimentd.py
galileo/cli/galileo.py
galileo/cli/shell.py
galileo/cli/worker.py
galileo/controller/__init__.py
galileo/controller/cluster.py
galileo/controller/experiment.py
galileo/experiment/__init__.py
galileo/experiment/experimentd.py
galileo/experiment/runner.py
galileo/experiment/service/__init__.py
galileo/experiment/service/experiment.py
galileo/shell/__init__.py
galileo/shell/printer.py
galileo/shell/shell.py
galileo/webapp/__init__.py
galileo/webapp/app.py
galileo/webapp/gunicorn.conf.py
galileo/webapp/wsgi.py
galileo/worker/__init__.py
galileo/worker/api.py
galileo/worker/client.py
galileo/worker/context.py
galileo/worker/daemon.py
galileo/worker/random.py
mc2_galileo.egg-info/PKG-INFO
mc2_galileo.egg-info/SOURCES.txt
mc2_galileo.egg-info/dependency_links.txt
mc2_galileo.egg-info/entry_points.txt
mc2_galileo.egg-info/requires.txt
mc2_galileo.egg-info/top_level.txt
tests/__init__.py
tests/test_util.py
tests/testutils.py
tests/api/__init__.py
tests/api/test_experiment_resource.py
tests/api/test_experiments_resource.py
tests/api/test_service_resource.py
tests/api/test_worker_resource.py
tests/apps/__init__.py
tests/apps/test_app.py
tests/apps/test_loader.py
tests/apps/test_repository.py
tests/controller/__init__.py
tests/controller/test_cluster.py
tests/experiment/__init__.py
tests/experiment/test_experiment_controller.py
tests/experiment/test_experimentd.py
tests/shell/__init__.py
tests/worker/__init__.py
tests/worker/test_client.py
tests/worker/test_worker.py