Metadata-Version: 2.1
Name: mc2-galileo
Version: 0.5.1
Summary: Galileo: Experimentation and Analytics Framework for MC2
Home-page: https://git.dsg.tuwien.ac.at/mc2/galileo
Author: Thomas Rausch
Author-email: t.rausch@dsg.tuwien.ac.at
License: UNKNOWN
Platform: UNKNOWN
Classifier: Programming Language :: Python :: 3
Classifier: Operating System :: OS Independent
